pydbrepo/__init__.py
pydbrepo/decorators/__init__.py
pydbrepo/decorators/entities.py
pydbrepo/descriptors/__init__.py
pydbrepo/descriptors/field.py
pydbrepo/drivers/__init__.py
pydbrepo/drivers/driver.py
pydbrepo/drivers/mongo.py
pydbrepo/drivers/mysql.py
pydbrepo/drivers/postgres.py
pydbrepo/drivers/qldb.py
pydbrepo/drivers/sqlite.py
pydbrepo/entity/__init__.py
pydbrepo/entity/entity.py
pydbrepo/entity/enum_entity.py
pydbrepo/errors/__init__.py
pydbrepo/errors/config.py
pydbrepo/errors/fields.py
pydbrepo/errors/queries.py
pydbrepo/errors/serialization.py
pydbrepo/helpers/__init__.py
pydbrepo/helpers/common/__init__.py
pydbrepo/helpers/common/common.py
pydbrepo/helpers/mongo/__init__.py
pydbrepo/helpers/mongo/mongo.py
pydbrepo/helpers/mysql/__init__.py
pydbrepo/helpers/mysql/mysql.py
pydbrepo/helpers/sql/__init__.py
pydbrepo/helpers/sql/sql.py
pydbrepo/helpers/sqlite/__init__.py
pydbrepo/helpers/sqlite/sqlite.py
pydbrepo/repository/__init__.py
pydbrepo/repository/mongo_repository.py
pydbrepo/repository/mysql_repository.py
pydbrepo/repository/postgres_repository.py
pydbrepo/repository/qldb_repository.py
pydbrepo/repository/repository.py
pydbrepo/repository/sqlite_repository.py
pydbrepo-0.8.0.dist-info/LICENSE
pydbrepo-0.8.0.dist-info/WHEEL
pydbrepo-0.8.0.dist-info/METADATA
pydbrepo-0.8.0.dist-info/RECORD
